{
  "_note": "Controls how AI law randomization works. 'excluded_law_categories' are skipped entirely. 'base_weights' set the default weight for each option (default 1.0 if omitted). 'trait_weights' are multipliers applied when the nation's primary culture has that trait — they stack multiplicatively across all three culture traits.",

  "excluded_law_categories": ["stability", "nomad_camp_type", "government_type", "succession_type", "vassal_type", "slavery_stance"],

  "base_weights": {
    "government_type": {
      "Fallen Monarchy":          1.0,
      "Fanatical Theocracy":      1.0,
      "Ruthless Meritocracy":     1.0,
      "Disjointed Anarchists":    1.0,
      "Archivist State":          0.0,
      "Chaotic Throng":           0.0,
      "Misfit Band":              0.0,
      "Iron-Fisted Dictatorship": 0.0,
      "Imperial Council":         0.0,
      "Sacred Vicar":             0.0,
      "Great Khanate":            0.0,
      "World Warden":             0.0
    },
    "succession_type": {
      "Strength":  1.0,
      "Inherited": 1.0,
      "Elected":   1.0
    },
    "conscription_type": {
      "Low":      1.0,
      "Moderate": 4.0,
      "High":     1.0,
      "Very High":0.0,
      "Total":    0.0,
      "Rebellion":0.0
    },
    "military_funding": {
      "Minimal":     0.5,
      "Substandard": 2.0,
      "Standard":    6.0,
      "Notable":     3,
      "Substantial": 1.0,
      "Extreme":     0.25
    },
    "magic_stance": {
      "Bureaucracy": 1.0,
      "Ceremonial":  1.0,
      "Creation":    1.0,
      "Destruction": 1.0,
      "Manifest":    1.0,
      "Persecution": 0.5
    },
    "centralization_law": {
      "Autonomous":    1.0,
      "Decentralized": 2.0,
      "Standard":      3.0,
      "Focused":       2.0,
      "Absolute":      1.0
    },
    "citizenship_stance": {
      "Free":       1.0,
      "Open":       4.0,
      "Restricted": 4.0,
      "Closed":     1.0
    },
    "foreign_acceptance": {
      "Oppression":  2.0,
      "Integration": 6.0,
      "Acceptance":  3.0,
      "Harmony":     1.0
    },
    "subject_stance": {
      "Suppression": 1.0,
      "Balanced":    4.0,
      "Benevolence": 1.0
    },
    "land_doctrine": {
      "Standard":  12.0,
      "Ambush":    1.0,
      "Horde":     1.0,
      "Militia":   1.0,
      "Safeguard": 1.0,
      "Shock":     1.0,
      "Volley":    1.0
    },
    "naval_doctrine": {
      "Standard":  6.0,
      "Fleet":     1.0,
      "Skirmish":  1.0,
      "Transport": 1.0
    },
    "diplomatic_stance": {
      "Belligerent":   10.0,
      "Cooperative":   20.0,
      "Expansionist":  20.0,
      "Extermination": 1.0,
      "Isolated":      5.0
    },
    "scientific_stance": {
      "Puritanical":   1.0,
      "Conservative":  5.0,
      "Pragmatic":     10.0,
      "Progressive":   6.0,
      "Radical":       2.0,
      "Revolutionary": 1.0
    },
    "economy_type": {
      "None":         1.0,
      "Millet":       0.0,
      "Raiding":      0.0,
      "Serfdom":      0.0,
      "Mercantilism": 0.0,
      "Guilds":       0.0
    },
    "expansion_stance": {
      "Limitless":  1.0,
      "Free":       5.0,
      "Restricted": 5.0,
      "Controlled": 1.0
    },
    "mercenary_law": {
      "No Mercenaries":    6.0,
      "Some Mercenaries":  10.0,
      "Mercenary Presence":5.0,
      "Mercenary Reliance":2.0,
      "Mercenary Military":1.0
    },
    "consumption_stance": {
      "Indulgence": 1.0,
      "Comfort":    3.0,
      "Standard":   10.0,
      "Rationing":  2.0
    },
    "tax_stance": {
      "Subsidized":  1.0,
      "No Taxes":    2.0,
      "Low":         10.0,
      "Moderate":    8.0,
      "High":        6.0,
      "Oppressive":  1.0
    }
  },

  "trait_weights": {
    "Militarist": {
      "military_funding": {
        "Minimal":     0.1,
        "Substandard": 0.25,
        "Standard":    0.5,
        "Notable":     3.0,
        "Substantial": 5.0,
        "Extreme":     3.0
      },
      "conscription_type": {
        "Low":    0.2,
        "High":   3.0
      },
      "land_doctrine": {
        "Horde":  4.0,
        "Shock":  4.0,
        "Ambush": 4.0
      },
      "diplomatic_stance": {
        "Belligerent":   5.0,
        "Expansionist":  2.0,
        "Cooperative":   0.25,
        "Extermination": 5.0
      }
    },

    "Pacifist": {
      "military_funding": {
        "Minimal":     4.0,
        "Substandard": 3.0,
        "Standard":    1.0,
        "Notable":     0.25,
        "Substantial": 0.1,
        "Extreme":     0.05
      },
      "conscription_type": {
        "Low":    3.0,
        "High":   0.25
      },
      "diplomatic_stance": {
        "Belligerent":   0.1,
        "Cooperative":   3.0,
        "Expansionist":  0.4,
        "Extermination": 0.0,
        "Isolated":      1.5
      }
    },

    "Mercantilist": {
      "mercenary_law": {
        "Some Mercenaries":  2.0,
        "Mercenary Presence":3.0,
        "Mercenary Reliance":4.0
      },
      "diplomatic_stance": {
        "Cooperative":  2.0,
        "Expansionist": 2.0,
        "Isolated":     0.1
      }
    },

    "Isolationist": {
      "diplomatic_stance": {
        "Isolated":     10.0,
        "Cooperative":  0.25,
        "Expansionist": 0.5,
        "Extermination": 5.0,
        "Belligerent":  0.5
      },
      "citizenship_stance": {
        "Closed":     5.0,
        "Restricted": 3.0,
        "Free":       0.1
      },
      "foreign_acceptance": {
        "Oppression":  4.0,
        "Integration": 0.5,
        "Acceptance":  0.25,
        "Harmony":     0.1
      },
      "expansion_stance": {
        "Limitless":  0.1,
        "Free":       0.25,
        "Restricted": 2.0,
        "Controlled": 3.0
      }
    },

    "Spiritualist": {
      "magic_stance": {
        "Ceremonial":  3.0,
        "Creation":    2.0,
        "Manifest":    2.0,
        "Persecution": 0.1
      },
      "government_type": {
        "Fanatical Theocracy": 3.0
      },
      "foreign_acceptance": {
        "Oppression":  2.0,
        "Integration": 4.0,
        "Acceptance":  0.5,
        "Harmony":     0.25
      },
      "scientific_stance": {
        "Puritanical":   2.0,
        "Conservative":  2.0,
        "Pragmatic":     0.75,
        "Progressive":   0.25,
        "Revolutionary": 0.1
      }
    },

    "Secular": {
      "magic_stance": {
        "Bureaucracy": 2.0,
        "Persecution": 2.0,
        "Ceremonial":  0.4
      },
      "government_type": {
        "Fanatical Theocracy": 0.1,
        "Sacred Vicar":        0.2
      },
      "scientific_stance": {
        "Puritanical":   0.2,
        "Conservative":  0.5,
        "Pragmatic":     1.0,
        "Progressive":   3.0,
        "Radical":       3.0,
        "Revolutionary": 3.0
      }
    },

    "Absolutist": {
      "centralization_law": {
        "Autonomous":    0.1,
        "Decentralized": 0.25,
        "Standard":      0.5,
        "Focused":       3.0,
        "Absolute":      6.0
      },
      "succession_type": {
        "Inherited": 2.5,
        "Elected":   0.3
      },
      "government_type": {
        "Disjointed Anarchists":    0.0
      },
      "tax_stance": {
        "High":       2.0,
        "Oppressive": 2.0,
        "Low":        0.3,
        "No Taxes":   0.1,
        "Subsidized": 0.25
      }
    },

    "Communalist": {
      "government_type": {
        "Disjointed Anarchists": 3.0
      },
      "citizenship_stance": {
        "Free":   3.0,
        "Open":   2.0,
        "Closed": 0.2
      },
      "tax_stance": {
        "Subsidized": 2.0,
        "No Taxes":   2.0,
        "Low":        2.0,
        "High":       0.4,
        "Oppressive": 0.1
      },
      "foreign_acceptance": {
        "Harmony":     4.0,
        "Acceptance":  3.0,
        "Oppression":  0.25
      }
    },

    "Egalitarian": {
      "citizenship_stance": {
        "Free":     4.0,
        "Open":     3.0,
        "Closed":   0.1
      },
      "foreign_acceptance": {
        "Harmony":    3.0,
        "Acceptance": 2.0,
        "Oppression": 0.1
      },
      "succession_type": {
        "Elected": 5,
        "Inherited": 0.5,
        "Strength": 0.5
      }
    },

    "Individualist": {
      "citizenship_stance": {
        "Free":       2.5,
        "Open":       1.5,
        "Closed":     0.25
      },
      "tax_stance": {
        "Subsidized": 0.1,
        "No Taxes":   3.0,
        "Low":        2.0,
        "Moderate":   1.0,
        "High":       0.5,
        "Oppressive": 0.1
      },
      "centralization_law": {
        "Autonomous":    2.0,
        "Decentralized": 2.0,
        "Absolute":      0.1
      },
      "mercenary_law": {
        "Some Mercenaries":  1.5,
        "Mercenary Presence":2.0
      }
    },

    "Traditionalist": {
      "scientific_stance": {
        "Puritanical":   2.0,
        "Conservative":  3.0,
        "Pragmatic":     1.0,
        "Progressive":   0.25,
        "Radical":       0.1,
        "Revolutionary": 0.05
      },
      "succession_type": {
        "Inherited": 2.5,
        "Elected":   0.25
      },
      "government_type": {
        "Fallen Monarchy":  2.5
      }
    },

    "Progressive": {
      "scientific_stance": {
        "Puritanical":   0.1,
        "Conservative":  0.25,
        "Pragmatic":     1.0,
        "Progressive":   2.0,
        "Radical":       3.0,
        "Revolutionary": 4.0
      },
      "succession_type": {
        "Elected":   2.5,
        "Inherited": 0.5,
        "Strength":  0.5
      }
    }
  }
}
